Metadata-Version: 1.0
Name: Pri-Matrix-algebra
Version: 0.1
Summary: matrixp
Home-page: UNKNOWN
Author: UNKNOWN
Author-email: UNKNOWN
License: UNKNOWN
Platform: UNKNOWN
